esn_lab/__init__.py
esn_lab/model/esn.py
esn_lab/optim/optim.py
esn_lab/pipeline/train/trainer.py
esn_lab/runner/train/tenfold.py
esn_lab/runner/train/tenfold_parallel.py
esn_lab/utils/activate_func.py
esn_lab-0.2.0.dist-info/licenses/LICENSE
esn_lab-0.2.0.dist-info/METADATA
esn_lab-0.2.0.dist-info/WHEEL
esn_lab-0.2.0.dist-info/top_level.txt
esn_lab-0.2.0.dist-info/RECORD
