Metadata-Version: 2.4
Name: esn-lab
Version: 0.2.0
Summary: A Python package for Echo State Network experiments.
License: MIT License
Project-URL: Homepage, https://github.com/Applica-760/esn-lab
Project-URL: Repository, https://github.com/Applica-760/esn-lab
Project-URL: Bug Tracker, https://github.com/Applica-760/esn-lab/issues
Classifier: Development Status :: 3 - Alpha
Classifier: License :: OSI Approved :: MIT License
Classifier: Programming Language :: Python :: 3
Classifier: Programming Language :: Python :: 3.10
Classifier: Programming Language :: Python :: 3.11
Classifier: Intended Audience :: Science/Research
Classifier: Topic :: Scientific/Engineering
License-File: LICENSE
Requires-Dist: numpy
Requires-Dist: matplotlib
Requires-Dist: pandas
Requires-Dist: opencv-python
Requires-Dist: PyYAML
Requires-Dist: omegaconf
Requires-Dist: networkx
Requires-Dist: tqdm
Provides-Extra: gpu
Requires-Dist: cupy-cuda13x; extra == "gpu"
Provides-Extra: test
Requires-Dist: pytest>=7.0.0; extra == "test"
Requires-Dist: pytest-cov>=4.0.0; extra == "test"
Dynamic: license-file
